livekit/plugins/reverie/__init__.py
livekit/plugins/reverie/log.py
livekit/plugins/reverie/stt.py
livekit/plugins/reverie/version.py
livekit_plugins_reverie-1.0.0.dist-info/METADATA
livekit_plugins_reverie-1.0.0.dist-info/WHEEL
livekit_plugins_reverie-1.0.0.dist-info/RECORD
