Metadata-Version: 2.4
Name: livekit-plugins-reverie
Version: 1.0.0
Summary: Agent Framework plugin for services using Reverie's API.
Project-URL: Documentation, https://docs.reverieinc.com/api-reference/speech-to-text-streaming
Project-URL: Website, https://reverieinc.com/
Project-URL: Source, https://github.com/reverieinc/livekit-plugins-reverie
Author-email: Reverie Speech Team <speech.team@reverieinc.com>
License-Expression: Apache-2.0
Keywords: ASR,STT,audio,hindi,indic languages,livekit,realtime,video,webrtc
Classifier: Intended Audience :: Developers
Classifier: License :: OSI Approved :: Apache Software License
Classifier: Programming Language :: Python :: 3
Classifier: Programming Language :: Python :: 3 :: Only
Classifier: Programming Language :: Python :: 3.9
Classifier: Programming Language :: Python :: 3.10
Classifier: Topic :: Multimedia :: Sound/Audio
Classifier: Topic :: Multimedia :: Video
Classifier: Topic :: Scientific/Engineering :: Artificial Intelligence
Requires-Python: >=3.9.0
Requires-Dist: livekit-agents[codecs]>=1.2.2
Requires-Dist: numpy>=1.26
